README.txt
setup.py
KnitCrypter/__init__.py
KnitCrypter/pkg_utils/_Assignment_Handler.py
KnitCrypter/pkg_utils/_Context_Manager.py
KnitCrypter/pkg_utils/__init__.py
KnitCrypter/pkg_utils/encrypt_utils/_Character_Struct.py
KnitCrypter/pkg_utils/encrypt_utils/_File_Struct.py
KnitCrypter/pkg_utils/encrypt_utils/_Needle_Struct.py
KnitCrypter/pkg_utils/encrypt_utils/_Number_Struct.py
KnitCrypter/pkg_utils/encrypt_utils/__init__.py
KnitCrypter/pkg_utils/encrypt_utils/error_checks/_Encrypt_Cases.py
KnitCrypter/pkg_utils/encrypt_utils/error_checks/_Encrypt_Errors.py
KnitCrypter/pkg_utils/encrypt_utils/error_checks/__init__.py
KnitCryption.egg-info/PKG-INFO
KnitCryption.egg-info/SOURCES.txt
KnitCryption.egg-info/dependency_links.txt
KnitCryption.egg-info/requires.txt
KnitCryption.egg-info/top_level.txt