Metadata-Version: 1.0
Name: KnitCryption
Version: 2.0.7
Summary: Encrytion package to assist in hiding data
Home-page: https://github.com/WilkinsonK/KnitCryption
Author: Keenan W. Wilkinson
Author-email: keenanwilkinson@outlook.com
License: GPL-3.0 license
Platform: UNKNOWN
